universal_evasion_attacks/__init__.py
universal_evasion_attacks/config.py
universal_evasion_attacks/master/master_params.json
universal_evasion_attacks-1.0.0.dist-info/LICENSE
universal_evasion_attacks-1.0.0.dist-info/METADATA
universal_evasion_attacks-1.0.0.dist-info/WHEEL
universal_evasion_attacks-1.0.0.dist-info/top_level.txt
universal_evasion_attacks-1.0.0.dist-info/RECORD
