Metadata-Version: 2.1
Name: universal-evasion-attacks
Version: 1.0.0
Summary: Security protocols for estimating adversarial robustness of machine learning models for both tabular and image datasets. This package implements a set of evasion attacks based on heuristic optimization algorithms, and complex cost functions to give reliable results for tabular problems.
Home-page: https://github.com/TortueSagace/universal_evasion_attacks
Author: Alexandre Le Mercier
Author-email: alexandre.le.mercier@ulb.be
License: MIT
Classifier: Intended Audience :: Developers
Classifier: License :: OSI Approved :: MIT License
Classifier: Programming Language :: Python
Classifier: Programming Language :: Python :: 3
Classifier: Programming Language :: Python :: 3.6
Classifier: Programming Language :: Python :: 3.7
Classifier: Programming Language :: Python :: 3.8
Classifier: Programming Language :: Python :: 3.9
Classifier: Programming Language :: Python :: 3.10
Classifier: Programming Language :: Python :: 3.11
Classifier: Programming Language :: Python :: 3.12
Classifier: Programming Language :: Python :: 3.13
Classifier: Operating System :: OS Independent
License-File: LICENSE
Requires-Dist: numpy
Requires-Dist: matplotlib
Requires-Dist: tqdm
Requires-Dist: scikit-learn
Requires-Dist: xgboost
Requires-Dist: lightgbm
Requires-Dist: pandas
Requires-Dist: seaborn
Requires-Dist: optuna
